{
  "targetPath": "/path/to/project",
  "score": 100,
  "summary": {
    "passed": 13,
    "warned": 0,
    "failed": 0
  },
  "checks": [
    {
      "id": "readme",
      "label": "README",
      "status": "pass",
      "message": "README.md exists.",
      "weight": 20,
      "points": 20
    },
    {
      "id": "license",
      "label": "License",
      "status": "pass",
      "message": "A license file exists.",
      "weight": 15,
      "points": 15
    },
    {
      "id": "gitignore",
      "label": "Git ignore",
      "status": "pass",
      "message": ".gitignore exists.",
      "weight": 10,
      "points": 10
    },
    {
      "id": "ci-workflow",
      "label": "CI workflow",
      "status": "pass",
      "message": "A GitHub Actions workflow exists.",
      "weight": 10,
      "points": 10
    },
    {
      "id": "readme-installation",
      "label": "README installation",
      "status": "pass",
      "message": "README includes installation instructions.",
      "weight": 10,
      "points": 10
    },
    {
      "id": "readme-usage",
      "label": "README usage",
      "status": "pass",
      "message": "README includes usage instructions.",
      "weight": 10,
      "points": 10
    },
    {
      "id": "readme-testing",
      "label": "README testing",
      "status": "pass",
      "message": "README explains how to run tests.",
      "weight": 10,
      "points": 10
    },
    {
      "id": "readme-examples",
      "label": "README examples",
      "status": "pass",
      "message": "README includes command examples.",
      "weight": 5,
      "points": 5
    },
    {
      "id": "package-metadata",
      "label": "Package metadata",
      "status": "pass",
      "message": "package.json includes name and version.",
      "weight": 5,
      "points": 5
    },
    {
      "id": "node-test-script",
      "label": "Node test script",
      "status": "pass",
      "message": "package.json defines a test script.",
      "weight": 10,
      "points": 10
    },
    {
      "id": "node-build-script",
      "label": "Node build script",
      "status": "pass",
      "message": "package.json defines a build script.",
      "weight": 5,
      "points": 5
    },
    {
      "id": "ci-test-command",
      "label": "CI test command",
      "status": "pass",
      "message": "GitHub Actions runs the test script.",
      "weight": 0,
      "points": 0
    },
    {
      "id": "ci-build-command",
      "label": "CI build command",
      "status": "pass",
      "message": "GitHub Actions runs the build script.",
      "weight": 0,
      "points": 0
    }
  ],
  "recommendations": []
}
